{
  "nodes": [
    {
      "version": "4.10.0-0.nightly-2021-12-03-213835",
      "payload": "registry.ci.openshift.org/ocp/release@sha256:756d0c474165d49d697ec69b768476c53f2c8be6300f5c31303dd31ee8dd4b5d"
    },
    {
      "version": "4.10.0-0.nightly-2021-12-06-162419",
      "payload": "registry.ci.openshift.org/ocp/release@sha256:e4792120595f7ce643560fb5df1f3da56e89f0ef5d90a70886fa9159c0490c50"
    }
  ],
  "conditionalEdges":[
    {
      "edges": [
        {"from": "4.10.0-0.nightly-2021-12-03-213835", "to": "4.10.0-0.nightly-2021-12-06-162419"}
      ],
      "risks": [
        {
          "url": "https://invalid.com/a",
          "name": "Invalid risk name",
          "message": "Invalid risk name",
          "matchingRules": [
            {
              "type": "Always"
            }
          ]
        }
      ]
    }
  ]
}

