{
  "nodes": [
    {
      "version": "4.11.0-0.nightly-2022-02-18-121223",
      "payload": "registry.ci.openshift.org/ocp/release@sha256:f23f34b758832f93a894e897429180f3c727d05594aa453c02ccb17e01319d6f",
      "metadata": {
	"io.openshift.upgrades.graph.release.channels": "stable-4.11"
      }
    },
    {
      "version": "4.11.0-0.nightly-2022-02-18-074624",
      "payload": "quay.io/openshift-release-dev/ocp-release@sha256:1ef574412bafb68cd21432e37179fa48a7d350953935366d48cadbf274b3c3c1",
      "metadata": {
        "io.openshift.upgrades.graph.release.channels": "stable-4.11"
      }
    }
  ],
  "edges": [
    [0,1]
  ]
}

